odoo/addons/edi_purchase_ubl_output_oca/README.rst
odoo/addons/edi_purchase_ubl_output_oca/__init__.py
odoo/addons/edi_purchase_ubl_output_oca/__manifest__.py
odoo/addons/edi_purchase_ubl_output_oca/components/__init__.py
odoo/addons/edi_purchase_ubl_output_oca/components/generate.py
odoo/addons/edi_purchase_ubl_output_oca/demo/edi_exchange_type.xml
odoo/addons/edi_purchase_ubl_output_oca/i18n/edi_purchase_ubl_output_oca.pot
odoo/addons/edi_purchase_ubl_output_oca/readme/CONFIGURATION.rst
odoo/addons/edi_purchase_ubl_output_oca/readme/CONTRIBUTORS.rst
odoo/addons/edi_purchase_ubl_output_oca/readme/DESCRIPTION.rst
odoo/addons/edi_purchase_ubl_output_oca/static/description/icon.png
odoo/addons/edi_purchase_ubl_output_oca/static/description/index.html
odoo14_addon_edi_purchase_ubl_output_oca-14.0.1.1.0.dist-info/METADATA
odoo14_addon_edi_purchase_ubl_output_oca-14.0.1.1.0.dist-info/WHEEL
odoo14_addon_edi_purchase_ubl_output_oca-14.0.1.1.0.dist-info/top_level.txt
odoo14_addon_edi_purchase_ubl_output_oca-14.0.1.1.0.dist-info/RECORD
